tzfpy-1.1.0.dist-info/METADATA
tzfpy-1.1.0.dist-info/WHEEL
tzfpy-1.1.0.dist-info/licenses/LICENSE
tzfpy-1.1.0.dist-info/licenses/LICENSE_ANTI_CSDN.md
tzfpy/__init__.py
tzfpy/__init__.pyi
tzfpy/py.typed
tzfpy/tzfpy.cpython-314t-aarch64-linux-gnu.so
tzfpy-1.1.0.dist-info/RECORD
